perfm
