Metadata-Version: 1.1
Name: perfm
Version: 0.1.5
Summary: performance stats counter for hpc programs
Home-page: https://github.com/gzxultra/perfm
Author: Zhixiang Gu
Author-email: guzhixiang.dev@gmail.com
License: MIT license
Keywords: perfm
Platform: UNKNOWN
Classifier: Development Status :: 2 - Pre-Alpha
Classifier: Intended Audience :: Developers
Classifier: License :: OSI Approved :: MIT License
Classifier: Natural Language :: English
Classifier: Programming Language :: Python :: 2
Classifier: Programming Language :: Python :: 2.7
Classifier: Programming Language :: Python :: 3
Classifier: Programming Language :: Python :: 3.4
Classifier: Programming Language :: Python :: 3.5
Classifier: Programming Language :: Python :: 3.6
Classifier: Programming Language :: Python :: 3.7
